{"image_path": "confirmed_data/images\\img_1753796202.jpg", "labels": []}
{"image_path": "confirmed_data/images\\img_1753796265.jpg", "labels": []}
{"image_path": "confirmed_data/images\\img_1753796372.jpg", "labels": []}
{"image_path": "confirmed_data/images\\img_1753796450.jpg", "labels": []}
{"image_path": "confirmed_data/images\\img_1753796516.jpg", "labels": []}
{"image_path": "confirmed_data/images\\img_1753796614.jpg", "labels": []}
{"image_path": "confirmed_data/images\\img_1753796711.jpg", "labels": []}
{"image_path": "confirmed_data/images\\img_1753796778.jpg", "labels": []}
{"image_path": "confirmed_data/images\\img_1753796847.jpg", "labels": []}
{"image_path": "confirmed_data/images\\img_1753796978.jpg", "labels": []}
{"image_path": "confirmed_data/images\\img_1753797184.jpg", "labels": []}
{"image_path": "confirmed_data/images\\img_1753797266.jpg", "labels": []}
{"image_path": "confirmed_data/images\\img_1753800284.jpg", "labels": ["gafas"]}
